drafting/__init__.py
drafting/beziers.py
drafting/blender.py
drafting/drawbot.py
drafting/color/__init__.py
drafting/color/html.py
drafting/fontgoggles/compile/__init__.py
drafting/fontgoggles/compile/compilerPool.py
drafting/fontgoggles/compile/dsCompiler.py
drafting/fontgoggles/compile/ttxCompiler.py
drafting/fontgoggles/compile/ufoCompiler.py
drafting/fontgoggles/compile/workServer.py
drafting/fontgoggles/font/__init__.py
drafting/fontgoggles/font/baseFont.py
drafting/fontgoggles/font/dsFont.py
drafting/fontgoggles/font/glyphDrawing.py
drafting/fontgoggles/font/otfFont.py
drafting/fontgoggles/font/ufoFont.py
drafting/fontgoggles/misc/__init__.py
drafting/fontgoggles/misc/decorators.py
drafting/fontgoggles/misc/ftFont.py
drafting/fontgoggles/misc/hbShape.py
drafting/fontgoggles/misc/opentypeTags.py
drafting/fontgoggles/misc/properties.py
drafting/fontgoggles/misc/rectTree.py
drafting/fontgoggles/misc/segmenting.py
drafting/fontgoggles/misc/textInfo.py
drafting/geometry/__init__.py
drafting/geometry/atom.py
drafting/geometry/curve.py
drafting/geometry/edge.py
drafting/geometry/geometrical.py
drafting/geometry/line.py
drafting/geometry/point.py
drafting/geometry/primitives.py
drafting/geometry/rect.py
drafting/grid/__init__.py
drafting/interpolation/__init__.py
drafting/pens/__drawbotpen.py
drafting/pens/axidrawpen.py
drafting/pens/blenderpen.py
drafting/pens/cairopen.py
drafting/pens/draftingpen.py
drafting/pens/draftingpens.py
drafting/pens/drawablepen.py
drafting/pens/drawbotpen.py
drafting/pens/jsonpen.py
drafting/pens/misc.py
drafting/pens/outlinepen.py
drafting/pens/svgpen.py
drafting/pens/translationpen.py
drafting/sh/__init__.py
drafting/sh/context.py
drafting/text/__init__.py
drafting/text/composer.py
drafting/text/reader.py
drafting/text/richtext.py
drafting/text/shaper.py
drafting/time/__init__.py
drafting/time/easing.py
drafting/time/loop.py
drafting/time/timeable.py
drafting/time/timeline.py
drafting-0.2.4.dist-info/LICENSE
drafting-0.2.4.dist-info/METADATA
drafting-0.2.4.dist-info/WHEEL
drafting-0.2.4.dist-info/top_level.txt
drafting-0.2.4.dist-info/RECORD
